instinct_py/__init__.py
instinct_py/device/InstinctDevice.py
instinct_py/device/__init__.py
instinct_py/device/configuration/__init__.py
instinct_py/device/configuration/base.py
instinct_py/device/device_config/__init__.py
instinct_py/device/device_config/manager.py
instinct_py/device/device_config/types.py
instinct_py/device/electrode/__init__.py
instinct_py/device/electrode/manager.py
instinct_py/device/electrode/types.py
instinct_py/device/sensors/__init__.py
instinct_py/device/sensors/manager.py
instinct_py/device/sensors/types.py
instinct_py/device/stream/__init__.py
instinct_py/device/stream/manager.py
instinct_py/device/stream/node.py
instinct_py/device/stream/pipe.py
instinct_py/device/stream/stream.py
instinct_py/device/stream/types.py
instinct_py/utils/http_client.py
instinct_py-1.5.1.dist-info/METADATA
instinct_py-1.5.1.dist-info/WHEEL
instinct_py-1.5.1.dist-info/RECORD
