Metadata-Version: 2.3
Name: instinct-py
Version: 1.5.1
Summary: Python SDK for controlling and interacting with Nexstem Instinct Devices
License: ISC
Author: Nexstem India Private Limited
Author-email: developers@nexstem.ai
Requires-Python: >=3.9,<4.0
Classifier: License :: OSI Approved
Classifier: Programming Language :: Python :: 3
Classifier: Programming Language :: Python :: 3.9
Classifier: Programming Language :: Python :: 3.10
Classifier: Programming Language :: Python :: 3.11
Classifier: Programming Language :: Python :: 3.12
Classifier: Programming Language :: Python :: 3.13
Requires-Dist: pydantic (>=2.6.3,<3.0.0)
Requires-Dist: requests (>=2.31.0,<3.0.0)
Requires-Dist: uuid (>=1.30,<2.0)
